rds/__init__.py
rds/id_generator.py
rds/rds_dict.py
rds/rds_list.py
rds/type_conversion.py
rds/utils.py
rds/rds_subtypes/__init__.py
rds/rds_subtypes/rds_sub_base.py
rds/rds_subtypes/rds_sub_dict.py
rds/rds_subtypes/rds_sub_list.py
py_rds-1.3.0.dist-info/LICENSE
py_rds-1.3.0.dist-info/METADATA
py_rds-1.3.0.dist-info/WHEEL
py_rds-1.3.0.dist-info/top_level.txt
py_rds-1.3.0.dist-info/RECORD
