Metadata-Version: 2.1
Name: py-rds
Version: 1.3.0
Summary: Python Redundant Data Storage Module
Home-page: https://github.com/TheElementalOfDestruction/rds
Author: Destiny Peterson (The Elemental of Destruction)
Author-email: arceusthe@gmail.com
License: GPL
Download-URL: https://github.com/TheElementalOfDestruction/rds/archives/master
Platform: UNKNOWN
